lineage/__init__.py
lineage/cli.py
lineage/integration.py
lineage/schema.py
lineage/snapshot.py
lineage/typedef_cli.py
lineage/ag_ui/client.py
lineage/agent/README.md
lineage/agent/__init__.py
lineage/agent/prompt_loader.py
lineage/agent/pydantic/__init__.py
lineage/agent/pydantic/__main__.py
lineage/agent/pydantic/ag_ui_handler.py
lineage/agent/pydantic/cli_agents.py
lineage/agent/pydantic/cli_runner.py
lineage/agent/pydantic/memory_observer.py
lineage/agent/pydantic/orchestrator.py
lineage/agent/pydantic/subagents.py
lineage/agent/pydantic/summary.py
lineage/agent/pydantic/types.py
lineage/agent/pydantic/utils.py
lineage/agent/pydantic/prompts/data_analyst.yaml.j2
lineage/agent/pydantic/prompts/data_engineer_copilot.yaml.j2
lineage/agent/pydantic/prompts/data_engineer_copilot_cost_optimized.yaml.j2
lineage/agent/pydantic/prompts/data_engineer_reconciler.yaml.j2
lineage/agent/pydantic/prompts/data_engineer_reconciler_cost_optimized.yaml.j2
lineage/agent/pydantic/prompts/data_insights.yaml.j2
lineage/agent/pydantic/prompts/data_investigator.yaml.j2
lineage/agent/pydantic/prompts/data_quality.yaml.j2
lineage/agent/pydantic/tools/__init__.py
lineage/agent/pydantic/tools/bash.py
lineage/agent/pydantic/tools/common.py
lineage/agent/pydantic/tools/data.py
lineage/agent/pydantic/tools/dbt.py
lineage/agent/pydantic/tools/filesystem.py
lineage/agent/pydantic/tools/git.py
lineage/agent/pydantic/tools/graph.py
lineage/agent/pydantic/tools/memory.py
lineage/agent/pydantic/tools/presentation.py
lineage/agent/pydantic/tools/ticketing.py
lineage/agent/pydantic/tools/todos.py
lineage/agent/utils/__init__.py
lineage/agent/utils/backend_hints.py
lineage/agent/utils/cursor.py
lineage/agent/utils/visualization.py
lineage/api/app.py
lineage/api/collector.py
lineage/api/pydantic.py
lineage/backends/README.md
lineage/backends/__init__.py
lineage/backends/config.py
lineage/backends/mcp_auto.py
lineage/backends/types.py
lineage/backends/utils.py
lineage/backends/data_query/__init__.py
typedef_data_intelligence-0.5.0.dist-info/METADATA
typedef_data_intelligence-0.5.0.dist-info/WHEEL
typedef_data_intelligence-0.5.0.dist-info/entry_points.txt
typedef_data_intelligence-0.5.0.dist-info/RECORD
