Metadata-Version: 2.4
Name: typedef-data-intelligence
Version: 0.5.0
Summary: Unified lineage management and AI-powered analytics platform for dbt projects
Project-URL: Homepage, https://typedef.ai
Project-URL: Repository, https://github.com/typedef-ai/data-intelligence
Project-URL: Issues, https://github.com/typedef-ai/data-intelligence/issues
Author-email: typedef <hello@typedef.ai>
License-Expression: LicenseRef-Proprietary
Keywords: analytics,data-engineering,dbt,lineage,tui
Classifier: Development Status :: 4 - Beta
Classifier: Environment :: Console
Classifier: Intended Audience :: Developers
Classifier: License :: Other/Proprietary License
Classifier: Operating System :: MacOS
Classifier: Operating System :: POSIX :: Linux
Classifier: Programming Language :: Python :: 3.12
Classifier: Programming Language :: Python :: 3.13
Classifier: Topic :: Database
Classifier: Topic :: Software Development :: Libraries :: Python Modules
Requires-Python: >=3.12
Requires-Dist: ag-ui-protocol>=0.1.0
Requires-Dist: anthropic>=0.45.0
Requires-Dist: chafa-py>=1.0.0
Requires-Dist: claude-agent-sdk
Requires-Dist: claude-telemetry[logfire]
Requires-Dist: click>=8.1.0
Requires-Dist: dbt-core>=1.7.0
Requires-Dist: dbt-snowflake>=1.7.0
Requires-Dist: falkordb
Requires-Dist: falkordblite>=0.7.0
Requires-Dist: fastapi>=0.104.0
Requires-Dist: fastmcp>=0.1.0
Requires-Dist: fenic[anthropic,google]>=0.6.0
Requires-Dist: graphiti-core
Requires-Dist: graphiti-core-falkordb
Requires-Dist: httpx>=0.25.0
Requires-Dist: jinja2>=3.1.0
Requires-Dist: kaleido>=1.1.0
Requires-Dist: linear-api
Requires-Dist: litellm>=1.78.5
Requires-Dist: logfire[fastapi]
Requires-Dist: markdown>=3.9
Requires-Dist: matplotlib>=3.7.0
Requires-Dist: mermaid-cli>=0.1.2
Requires-Dist: openlineage-dbt>=1.39.0
Requires-Dist: openlineage-python
Requires-Dist: pillow>=10.0.0
Requires-Dist: plotext>=5.3.2
Requires-Dist: plotly>=6.3.1
Requires-Dist: pydantic-ai>=1.23.0
Requires-Dist: pydantic-settings>=2.4.0
Requires-Dist: pydantic>=2.0
Requires-Dist: pymupdf==1.26.5
Requires-Dist: pyyaml>=6.0.0
Requires-Dist: rich>=13.0.0
Requires-Dist: snowflake-connector-python>=3.10.0
Requires-Dist: snowflake-labs-mcp>=0.1.0
Requires-Dist: sqlglot>=20.0.0
Requires-Dist: term-image>=0.7.0
Requires-Dist: textual>=6.6.0
Requires-Dist: uvicorn>=0.24.0
Provides-Extra: dev
Requires-Dist: pytest-asyncio>=0.21.0; extra == 'dev'
Requires-Dist: pytest>=7.4.0; extra == 'dev'
Requires-Dist: ruff>=0.1.0; extra == 'dev'
Requires-Dist: tiktoken>=0.11.0; extra == 'dev'
Provides-Extra: duckdb
Requires-Dist: dbt-duckdb>=1.7.0; extra == 'duckdb'
